infrahub/__init__.py
infrahub/auth.py
infrahub/auth_pkce.py
infrahub/components.py
infrahub/config.py
infrahub/context.py
infrahub/exceptions.py
infrahub/helpers.py
infrahub/lock.py
infrahub/log.py
infrahub/middleware.py
infrahub/models.py
infrahub/py.typed
infrahub/pytest_plugin.py
infrahub/server.py
infrahub/storage.py
infrahub/trace.py
infrahub/types.py
infrahub/utils.py
infrahub/visuals.py
infrahub/worker.py
infrahub/actions/__init__.py
infrahub/actions/constants.py
infrahub/actions/gather.py
infrahub/actions/models.py
infrahub/actions/parsers.py
infrahub/actions/schema.py
infrahub/actions/tasks.py
infrahub/actions/triggers.py
infrahub/api/__init__.py
infrahub/api/artifact.py
infrahub/api/auth.py
infrahub/api/dependencies.py
infrahub/api/exception_handlers.py
infrahub/api/exceptions.py
infrahub/api/file.py
infrahub/api/internal.py
infrahub/api/menu.py
infrahub/api/oauth2.py
infrahub/api/oidc.py
infrahub/api/query.py
infrahub/api/schema.py
infrahub/api/storage.py
infrahub/api/transformation.py
infrahub/api/diff/__init__.py
infrahub/api/diff/diff.py
infrahub/api/diff/validation_models.py
infrahub/api/static/redoc.standalone.js
infrahub/api/static/swagger-ui-bundle.js
infrahub/api/static/swagger-ui.css
infrahub/artifacts/__init__.py
infrahub/artifacts/models.py
infrahub/artifacts/tasks.py
infrahub/branch/__init__.py
infrahub/branch/merge_mutation_checker.py
infrahub/branch/tasks.py
infrahub/branch/triggers.py
infrahub/cli/__init__.py
infrahub/cli/constants.py
infrahub/cli/context.py
infrahub/cli/db.py
infrahub/cli/dev.py
infrahub/cli/events.py
infrahub/cli/git_agent.py
infrahub/cli/patch.py
infrahub/cli/server.py
infrahub/cli/tasks.py
infrahub/cli/upgrade.py
infrahub/cli/db_commands/__init__.py
infrahub/cli/db_commands/check_inheritance.py
infrahub/cli/db_commands/clean_duplicate_schema_fields.py
infrahub/computed_attribute/__init__.py
infrahub/computed_attribute/constants.py
infrahub/computed_attribute/gather.py
infrahub/computed_attribute/models.py
infrahub_server-1.6.1.dist-info/METADATA
infrahub_server-1.6.1.dist-info/WHEEL
infrahub_server-1.6.1.dist-info/entry_points.txt
infrahub_server-1.6.1.dist-info/licenses/LICENSE.txt
infrahub_server-1.6.1.dist-info/RECORD
