Metadata-Version: 2.4
Name: infrahub-server
Version: 1.6.1
Summary: Infrahub is taking a new approach to Infrastructure Management by providing a new generation of datastore to organize and control all the data that defines how an infrastructure should run.
Project-URL: Homepage, https://opsmill.com
Project-URL: Repository, https://github.com/opsmill/infrahub
Project-URL: Documentation, https://docs.infrahub.app/
Author-email: OpsMill <info@opsmill.com>
License-Expression: Apache-2.0
License-File: LICENSE.txt
Classifier: Intended Audience :: Developers
Classifier: Programming Language :: Python :: 3
Classifier: Programming Language :: Python :: 3.12
Requires-Python: <3.13,>=3.12
Requires-Dist: aio-pika<9.5,>=9.4
Requires-Dist: aiodataloader==0.4.0
Requires-Dist: ariadne-codegen==0.15.3
Requires-Dist: asgi-correlation-id==4.2.0
Requires-Dist: authlib==1.6.5
Requires-Dist: bcrypt<4.2,>=4.1
Requires-Dist: boto3==1.34.129
Requires-Dist: cachetools-async==0.0.5
Requires-Dist: click==8.1.7
Requires-Dist: deepdiff==8.6.1
Requires-Dist: dulwich==0.22.7
Requires-Dist: email-validator<2.2,>=2.1
Requires-Dist: fast-depends==2.4.12
Requires-Dist: fastapi-storages<0.4,>=0.3
Requires-Dist: fastapi==0.121.1
Requires-Dist: gitpython<4,>=3
Requires-Dist: graphene<3.5,>=3.4
Requires-Dist: gunicorn<24,>=23.0.0
Requires-Dist: jinja2<4,>=3
Requires-Dist: lunr<0.8,>=0.7.0.post1
Requires-Dist: nats-py==2.7.2
Requires-Dist: neo4j-rust-ext<5.29,>=5.28
Requires-Dist: neo4j<5.29,>=5.28
Requires-Dist: netaddr==1.3.0
Requires-Dist: netutils==1.12.0
Requires-Dist: numpy==1.26.2
Requires-Dist: opentelemetry-exporter-otlp-proto-grpc==1.28.1
Requires-Dist: opentelemetry-exporter-otlp-proto-http==1.28.1
Requires-Dist: opentelemetry-instrumentation-aio-pika==0.49b1
Requires-Dist: opentelemetry-instrumentation-fastapi==0.49b1
Requires-Dist: prefect-redis==0.2.6
Requires-Dist: prefect==3.5.0
Requires-Dist: pyarrow<15,>=14
Requires-Dist: pydantic-settings<2.9,>=2.8
Requires-Dist: pydantic<2.11,>=2.10
Requires-Dist: pyjwt<2.9,>=2.8
Requires-Dist: pytest<7.5,>=7.4
Requires-Dist: python-multipart==0.0.18
Requires-Dist: pyyaml<7,>=6
Requires-Dist: redis[hiredis]==6.0.0
Requires-Dist: rich<14,>=13
Requires-Dist: starlette-exporter<0.24,>=0.23
Requires-Dist: structlog==24.1.0
Requires-Dist: tomli>=1.1.0; python_version <= '3.11'
Requires-Dist: typer==0.19.2
Requires-Dist: ujson<6,>=5
Requires-Dist: uvicorn[standard]<0.33,>=0.32
Requires-Dist: whenever==0.9.3
